gpu_task_scheduler/__init__.py
gpu_task_scheduler/scheduler.py
gpu_task_scheduler-0.4.0.dist-info/licenses/LICENSE.txt
gpu_task_scheduler-0.4.0.dist-info/METADATA
gpu_task_scheduler-0.4.0.dist-info/WHEEL
gpu_task_scheduler-0.4.0.dist-info/top_level.txt
gpu_task_scheduler-0.4.0.dist-info/RECORD
