Metadata-Version: 2.4
Name: gpu_task_scheduler
Version: 0.4.0
Summary: A python lib to schedule deep learning tasks on available GPUs.
Author: sangyx
Classifier: Programming Language :: Python :: 3
Classifier: License :: OSI Approved :: MIT License
Classifier: Operating System :: OS Independent
Requires-Python: >=3.6
License-File: LICENSE.txt
Dynamic: author
Dynamic: classifier
Dynamic: description
Dynamic: description-content-type
Dynamic: license-file
Dynamic: requires-python
Dynamic: summary
